http_requester/__init__.py
http_requester/creds.py
http_requester/requester.py
http_requester-1.0.11.dist-info/WHEEL
http_requester-1.0.11.dist-info/METADATA
http_requester-1.0.11.dist-info/RECORD
